arivo/webhook/__init__.py
arivo/webhook/errors.py
arivo_webhook-1.1.1.dist-info/AUTHORS
arivo_webhook-1.1.1.dist-info/LICENSE
arivo_webhook-1.1.1.dist-info/METADATA
arivo_webhook-1.1.1.dist-info/WHEEL
arivo_webhook-1.1.1.dist-info/pbr.json
arivo_webhook-1.1.1.dist-info/top_level.txt
arivo_webhook-1.1.1.dist-info/RECORD
